[
  {
    "ayah": 1,
    "time": 4193
  },
  {
    "ayah": 2,
    "time": 11192
  },
  {
    "ayah": 3,
    "time": 27260
  },
  {
    "ayah": 4,
    "time": 32043
  },
  {
    "ayah": 5,
    "time": 53445
  },
  {
    "ayah": 6,
    "time": 76107
  },
  {
    "ayah": 7,
    "time": 113917
  },
  {
    "ayah": 8,
    "time": 122787
  },
  {
    "ayah": 9,
    "time": 131192
  },
  {
    "ayah": 10,
    "time": 143777
  },
  {
    "ayah": 11,
    "time": 171363
  },
  {
    "ayah": 12,
    "time": 204567
  },
  {
    "ayah": 13,
    "time": 227562
  },
  {
    "ayah": 14,
    "time": 238090
  },
  {
    "ayah": 15,
    "time": 256755
  },
  {
    "ayah": 16,
    "time": 290017
  },
  {
    "ayah": 17,
    "time": 319792
  },
  {
    "ayah": 18,
    "time": 356465
  },
  {
    "ayah": 19,
    "time": 376202
  },
  {
    "ayah": 20,
    "time": 385629
  },
  {
    "ayah": 21,
    "time": 409360
  },
  {
    "ayah": 22,
    "time": 421727
  },
  {
    "ayah": 23,
    "time": 434259
  },
  {
    "ayah": 24,
    "time": 447112
  },
  {
    "ayah": 25,
    "time": 466156
  },
  {
    "ayah": 26,
    "time": 512407
  },
  {
    "ayah": 27,
    "time": 542346
  },
  {
    "ayah": 28,
    "time": 576561
  },
  {
    "ayah": 29,
    "time": 589503
  }
]